ptranking/__init__.py
ptranking/ltr_global.py
ptranking/base/__init__.py
ptranking/base/neural_utils.py
ptranking/base/ranker.py
ptranking/data/__init__.py
ptranking/data/data_utils.py
ptranking/ltr_adhoc/__init__.py
ptranking/ltr_adhoc/eval/__init__.py
ptranking/ltr_adhoc/eval/eval_utils.py
ptranking/ltr_adhoc/eval/ltr.py
ptranking/ltr_adhoc/eval/parameter.py
ptranking/ltr_adhoc/listwise/__init__.py
ptranking/ltr_adhoc/listwise/approxNDCG.py
ptranking/ltr_adhoc/listwise/lambdaloss.py
ptranking/ltr_adhoc/listwise/lambdarank.py
ptranking/ltr_adhoc/listwise/listmle.py
ptranking/ltr_adhoc/listwise/listnet.py
ptranking/ltr_adhoc/listwise/rank_cosine.py
ptranking/ltr_adhoc/listwise/st_listnet.py
ptranking/ltr_adhoc/listwise/wassrank/__init__.py
ptranking/ltr_adhoc/listwise/wassrank/wassRank.py
ptranking/ltr_adhoc/listwise/wassrank/wasserstein_cost_mat.py
ptranking/ltr_adhoc/listwise/wassrank/wasserstein_loss_layer.py
ptranking/ltr_adhoc/pairwise/__init__.py
ptranking/ltr_adhoc/pairwise/ranknet.py
ptranking/ltr_adhoc/pointwise/__init__.py
ptranking/ltr_adhoc/pointwise/rank_mse.py
ptranking/ltr_adhoc/util/__init__.py
ptranking/ltr_adhoc/util/bin_utils.py
ptranking/ltr_adhoc/util/gather_utils.py
ptranking/ltr_adhoc/util/one_hot_utils.py
ptranking/ltr_adhoc/util/sampling_utils.py
ptranking/ltr_adversarial/__init__.py
ptranking/ltr_adversarial/base/__init__.py
ptranking/ltr_adversarial/base/ad_machine.py
ptranking/ltr_adversarial/base/ad_player.py
ptranking/ltr_adversarial/eval/__init__.py
ptranking/ltr_adversarial/eval/ad_parameter.py
ptranking/ltr_adversarial/eval/ltr_adversarial.py
ptranking/ltr_adversarial/listwise/__init__.py
ptranking/ltr_adversarial/listwise/irgan_list.py
ptranking/ltr_adversarial/listwise/list_discriminator.py
ptranking/ltr_adversarial/listwise/list_generator.py
ptranking/ltr_adversarial/pairwise/__init__.py
ptranking/ltr_adversarial/pairwise/irgan_pair.py
ptranking/ltr_adversarial/pairwise/pair_discriminator.py
ptranking-0.0.5.dist-info/LICENSE
ptranking-0.0.5.dist-info/METADATA
ptranking-0.0.5.dist-info/WHEEL
ptranking-0.0.5.dist-info/top_level.txt
ptranking-0.0.5.dist-info/RECORD
