Metadata-Version: 2.1
Name: ptranking
Version: 0.0.5
Summary: A library of scalable and extendable implementations of typical learning-to-rank methods based on PyTorch.
Home-page: https://github.com/wildltr/ptranking
Author: II-Research
Author-email: yuhaitao@slis.tsukuba.ac.jp
License: MIT License
Keywords: Learning-to-rank,PyTorch
Platform: UNKNOWN
Classifier: Development Status :: 3 - Alpha
Classifier: Programming Language :: Python :: 3
Classifier: License :: OSI Approved :: MIT License
Classifier: Operating System :: OS Independent
Requires-Dist: numpy
Requires-Dist: tqdm
